bhepop2/__init__.py
bhepop2/analysis.py
bhepop2/functions.py
bhepop2/optim.py
bhepop2/tools.py
bhepop2/utils.py
bhepop2/enrichment/__init__.py
bhepop2/enrichment/base.py
bhepop2/enrichment/bhepop2.py
bhepop2/enrichment/uniform.py
bhepop2/sources/__init__.py
bhepop2/sources/base.py
bhepop2/sources/global_distribution.py
bhepop2/sources/marginal_distributions.py
bhepop2-2.0.1.dist-info/licenses/LICENSE.txt
tests/__init__.py
tests/conftest.py
tests/test_analysis.py
tests/test_functions.py
tests/test_tools.py
tests/test_utils.py
tests/enrichment/__init__.py
tests/enrichment/test_base.py
tests/enrichment/test_bhepop2.py
tests/enrichment/test_uniform.py
tests/sources/__init__.py
tests/sources/test_base.py
tests/sources/test_global_distribution.py
tests/sources/test_marginal_distributions.py
bhepop2-2.0.1.dist-info/METADATA
bhepop2-2.0.1.dist-info/WHEEL
bhepop2-2.0.1.dist-info/top_level.txt
bhepop2-2.0.1.dist-info/RECORD
