Metadata-Version: 2.4
Name: bhepop2
Version: 2.0.1
Summary: Synthetic population enrichment from aggregated data
Home-page: https://github.com/tellae/bhepop2
Author: UGE & Tellae
Author-email: contact@tellae.fr
License: CECILL-B
Classifier: Development Status :: 3 - Alpha
Classifier: Intended Audience :: Science/Research
Classifier: Intended Audience :: Developers
Classifier: Topic :: Scientific/Engineering
Classifier: Programming Language :: Python :: 3 :: Only
Classifier: Programming Language :: Python :: 3.10
Classifier: Programming Language :: Python :: 3.11
Classifier: License :: CeCILL-B Free Software License Agreement (CECILL-B)
Requires-Python: >=3.10
License-File: LICENSE.txt
Requires-Dist: numpy>=2.1.0
Requires-Dist: pandas>=2.2.2
Requires-Dist: xlrd>=2.0.1
Requires-Dist: scipy>=1.14.0
Requires-Dist: scikit-learn>=1.5.1
Requires-Dist: plotly>=5.12.0
Dynamic: author
Dynamic: author-email
Dynamic: classifier
Dynamic: description
Dynamic: description-content-type
Dynamic: home-page
Dynamic: license
Dynamic: license-file
Dynamic: requires-dist
Dynamic: requires-python
Dynamic: summary
